odoo9_addon_pos_access_right-9.0.1.0.0.99.dev22-py3.6-nspkg.pth
odoo_addons/pos_access_right/README.rst
odoo_addons/pos_access_right/__init__.py
odoo_addons/pos_access_right/__openerp__.py
odoo_addons/pos_access_right/demo/res_groups.yml
odoo_addons/pos_access_right/i18n/ca.po
odoo_addons/pos_access_right/i18n/fr.po
odoo_addons/pos_access_right/i18n/pos_access_right.pot
odoo_addons/pos_access_right/models/__init__.py
odoo_addons/pos_access_right/models/pos_config.py
odoo_addons/pos_access_right/security/res_groups.yml
odoo_addons/pos_access_right/static/description/admin_numpad.png
odoo_addons/pos_access_right/static/description/demo_error.png
odoo_addons/pos_access_right/static/description/demo_numpad.png
odoo_addons/pos_access_right/static/description/icon.png
odoo_addons/pos_access_right/static/description/new_groups.png
odoo_addons/pos_access_right/static/src/css/pos_access_right.css
odoo_addons/pos_access_right/static/src/js/pos_access_right.js
odoo_addons/pos_access_right/static/src/xml/templates.xml
odoo9_addon_pos_access_right-9.0.1.0.0.99.dev22.dist-info/METADATA
odoo9_addon_pos_access_right-9.0.1.0.0.99.dev22.dist-info/WHEEL
odoo9_addon_pos_access_right-9.0.1.0.0.99.dev22.dist-info/namespace_packages.txt
odoo9_addon_pos_access_right-9.0.1.0.0.99.dev22.dist-info/top_level.txt
odoo9_addon_pos_access_right-9.0.1.0.0.99.dev22.dist-info/RECORD
