Metadata-Version: 2.1
Name: odoo9-addon-pos-access-right
Version: 9.0.1.0.0.99.dev22
Summary: Point of Sale - Extra Access Right for certain actions
Home-page: http://www.lalouve.net/
Author: La Louve, GRAP, Odoo Community Association (OCA)
Author-email: support@odoo-community.org
License: AGPL-3
Platform: UNKNOWN
Classifier: Programming Language :: Python
Classifier: Framework :: Odoo
Classifier: License :: OSI Approved :: GNU Affero General Public License v3
Requires-Python: ~=2.7
Requires-Dist: odoo (<9.1a,>=9.0a)
